MANIFEST.in
README.txt
setup.py
src/asm/__init__.py
src/asm.cms.egg-info/PKG-INFO
src/asm.cms.egg-info/SOURCES.txt
src/asm.cms.egg-info/dependency_links.txt
src/asm.cms.egg-info/not-zip-safe
src/asm.cms.egg-info/requires.txt
src/asm.cms.egg-info/top_level.txt
src/asm/cms/__init__.py
src/asm/cms/asset.py
src/asm/cms/cms.py
src/asm/cms/configure.zcml
src/asm/cms/edition.py
src/asm/cms/ftesting.zcml
src/asm/cms/homepage.py
src/asm/cms/htmlpage.py
src/asm/cms/importer.py
src/asm/cms/interfaces.py
src/asm/cms/news.py
src/asm/cms/page.py
src/asm/cms/replace.py
src/asm/cms/search.py
src/asm/cms/testing.py
src/asm/cms/testutils.py
src/asm/cms/typography.py
src/asm/cms/utils.py
src/asm/cms/generations/__init__.py
src/asm/cms/generations/configure.zcml
src/asm/cms/generations/evolve1.py
src/asm/cms/generations/evolve2.py
src/asm/cms/generations/evolve3.py
src/asm/cms/generations/evolve4.py
src/asm/cms/generations/evolve5.py
src/asm/cms/generations/evolve6.py
src/asm/cms/generations/evolve7.py
src/asm/cms/generations/install.py
src/asm/cms/tests/__init__.py
src/asm/cms/tests/pencil.png
src/asm/cms/tests/test_asset.py
src/asm/cms/tests/test_edition.py
src/asm/cms/tests/test_htmlpage.py
src/asm/cms/tests/test_import.py
src/asm/cms/tests/test_page.py
src/asm/cms/tests/test_replace.py
src/asm/cms/tests/test_typography.py
src/asm/cms/tests/test_utils.py