Metadata-Version: 1.0
Name: asm.cms
Version: 0.1.6
Summary: Assembly Website CMS
Home-page: UNKNOWN
Author: Assembly Webcrew
Author-email: web@assembly.org
License: ZPL 2.1
Platform: UNKNOWN
